[1,["1d0e2b234","193f7b40a","70yJgAa2pPkpa1inhS8z1T","409DqlhAZMuLx4bXj3y/QD","a1WJScR9RLQ76TaFJs1ss0","ferI4zZt5K/pWMr81MhfKV","21jo99YnVJi7E+MW/G1u0K","8du6zQKaBM0oxmqXI5XmCh","7c8jq+kRhNSLHpwmlx3Jld","adTi9hX9xOfZOYMtRN5N0l","c2ZpSftlRJTbhZqcZ7LLGf","37UarVaNRGjqogHgFCf25W","515+OiZORKpLryYjMUExtY","dfzinpzk5IHpeF4T8Z+bSH","12KxW6dOhDf4Sx9wTYGU5L","9eK54hXQBD+KHzggtT9bt+","96UPwFsLdORbc6sYaXpzfZ","2bHTT6ufxBBrbhrQiUhccw","6fe68pzANCNr0CAKU+C4rG"],["_textureSetter","root","node","data"],["cc.SpriteFrame",["cc.Prefab",["_name"],2],["cc.Node",["_name","_components","_prefab"],2,9,4],["f2152SLPgdCS5hj/9udZTIO",["node","spr","icespr","Animspr"],3,1,12,12,12],["cc.PrefabInfo",["fileId","root"],2,1]],[[1,0,2],[2,0,1,2,2],[3,0,1,2,3,1],[4,0,1,2]],[[[{"name":"1","rect":[92,1758,74,73],"offset":[0,0],"originalSize":[74,73],"capInsets":[0,0,0,0]}],[0],0,[0],[0],[0]],[[{"name":"2","rect":[1327,1531,78,73],"offset":[0,0],"originalSize":[78,73],"rotated":1,"capInsets":[0,0,0,0]}],[0],0,[0],[0],[1]],[[{"name":"1","rect":[469,1869,77,73],"offset":[0,0],"originalSize":[77,73],"capInsets":[0,0,0,0]}],[0],0,[0],[0],[0]],[[{"name":"6","rect":[555,1792,76,77],"offset":[0,0],"originalSize":[76,77],"rotated":1,"capInsets":[0,0,0,0]}],[0],0,[0],[0],[0]],[[{"name":"mapLight","rect":[551,1978,66,66],"offset":[0,0],"originalSize":[66,66],"capInsets":[0,0,0,0]}],[0],0,[0],[0],[1]],[[{"name":"1","rect":[709,1567,78,73],"offset":[0,0],"originalSize":[78,73],"capInsets":[0,0,0,0]}],[0],0,[0],[0],[0]],[[{"name":"5","rect":[680,1832,74,73],"offset":[0,0],"originalSize":[74,73],"rotated":1,"capInsets":[0,0,0,0]}],[0],0,[0],[0],[0]],[[{"name":"mapBaseItem","rect":[1334,1383,66,66],"offset":[0,0],"originalSize":[66,66],"capInsets":[0,0,0,0]}],[0],0,[0],[0],[1]],[[{"name":"1","rect":[379,1974,60,59],"offset":[-1,0.5],"originalSize":[80,80],"rotated":1,"capInsets":[0,0,0,0]}],[0],0,[0],[0],[0]],[[{"name":"1","rect":[311,1817,76,77],"offset":[0,0],"originalSize":[76,77],"rotated":1,"capInsets":[0,0,0,0]}],[0],0,[0],[0],[0]],[[{"name":"mapBaseItem","rect":[1334,1455,66,66],"offset":[0,0],"originalSize":[66,66],"capInsets":[0,0,0,0]}],[0],0,[0],[0],[1]],[[[0,"SprManager"],[1,"SprManager",[[2,-2,[[null,0,1,2,3,4,5,6,7,8],0,6,6,6,6,6,6,6,6,6],[[null,9,10,11,null],0,6,6,6,0],[[null,12,13,14,15,16],0,6,6,6,6,6]]],[3,"00puh0Eu1IbKB9lzPwZceT",-1]]],0,[0,1,1,0,2,1,0,3,1,2],[0,0,0,0,0,0,0,0,0,0,0,0,0,0,0,0,0],[-2,-3,-4,-5,-6,-7,-8,-9,-10,-2,-3,-4,-2,-3,-4,-5,-6],[2,3,4,5,6,7,8,9,10,11,12,13,14,15,16,17,18]],[[{"name":"mapBaseItem","rect":[82,1975,69,69],"offset":[0.5,0],"originalSize":[70,69],"capInsets":[0,0,0,0]}],[0],0,[0],[0],[0]],[[{"name":"1","rect":[3,1948,77,73],"offset":[0,0],"originalSize":[77,73],"rotated":1,"capInsets":[0,0,0,0]}],[0],0,[0],[0],[0]]]]